mpl_chord/__init__.py
mpl_chord/example.png
mpl_chord/matplotlib_chord.py
matplotlib_chord_diagram-0.0.4.dist-info/AUTHORS.rst
matplotlib_chord_diagram-0.0.4.dist-info/LICENSE.txt
matplotlib_chord_diagram-0.0.4.dist-info/METADATA
matplotlib_chord_diagram-0.0.4.dist-info/WHEEL
matplotlib_chord_diagram-0.0.4.dist-info/top_level.txt
matplotlib_chord_diagram-0.0.4.dist-info/RECORD
