Metadata-Version: 2.1
Name: matplotlib-chord-diagram
Version: 0.0.4
Summary: Add a short description here!
Home-page: https://github.com/evanr70/matplotlib-chord-diagram
Author: Evan
Author-email: evanr70@gmail.com
License: mit
Platform: any
Classifier: Development Status :: 4 - Beta
Classifier: Programming Language :: Python
Requires-Dist: numpy
Requires-Dist: matplotlib
Provides-Extra: testing
Requires-Dist: pytest ; extra == 'testing'
Requires-Dist: pytest-cov ; extra == 'testing'
